divisor/rtl/shift/shift.v
//---------------------------------------------------------------------------
// SharkBoad ExampleModule
// Josnelihurt Rodriguez - Fredy Segura Q.
// josnelihurt@gmail.com
// Top Level Design for the Xilinx Spartan 3-100E Device
//---------------------------------------------------------------------------



/*#
# SharkBoad
# Copyright (C) 2012 Bogotá, Colombia
#
# This program is free software: you can redistribute it and/or modify
# it under the terms of the GNU General Public License as published by
# the Free Software Foundation, version 3 of the License.
#
# This program is distributed in the hope that it will be useful,
# but WITHOUT ANY WARRANTY; without even the implied warranty of
# MERCHANTABILITY or FITNESS FOR A PARTICULAR PURPOSE.  See the
# GNU General Public License for more details.
#
# You should have received a copy of the GNU General Public License
# along with this program.  If not, see <http://www.gnu.org/licenses/>.
#*/
// Based on Pong P. Chu - FPGA Prototyping by Verilog Examples 
// Listing 4.11
module shift
   #(
    parameter N=8 // number of bits in counter
   )
   (
    input wire rst,cont,equal,
    input wire [N-1:0] dividiendo,n_valor,
    output wire [N-1:0] q
   );

   //signal declaration
   reg [N-1:0] select_bit;
   reg [N-1:0] salida;
   reg [N-1:0] r_dividiendo;
   wire [N-1:0] w_select_bit;
   wire [N-1:0] w_salida;

   // body
   // register
   always @(posedge cont, posedge rst) begin
     if (rst) begin
       // reset
       select_bit = N-1;
       salida = 8'b0;
       r_dividiendo = dividiendo;
     end
     else if (cont) begin
       salida = w_salida;
       select_bit = select_bit -1;
     end
   end

   always @(posedge equal) begin
     salida = n_valor;
   end

   // assign
   assign w_salida = (salida << 1) + r_dividiendo[select_bit];
   assign q = salida;
   assign w_select_bit = r_dividiendo[select_bit];

endmodule

divisor/rtl/comparador/comparador.v
module comparador
	//Parametros
	#(
		parameter N=8
	)
	//entradas y salidas
	(
		input wire [N-1:0] i_a,
		input wire [N-1:0] i_b,
		output wire o_signal,
		output wire [N-1:0] o_resta
	);

	//registros y señales


	//cuerpo del modulo
	assign o_signal = ((i_a>i_b))?1'b1:1'b0;
	assign o_resta = i_a-i_b;


endmodule

divisor/simulation/system_tb.v
//----------------------------------------------------------------------------
//
//----------------------------------------------------------------------------

/*#
# SharkBoad
# Copyright (C) 2012 Bogotá, Colombia
#
# This program is free software: you can redistribute it and/or modify
# it under the terms of the GNU General Public License as published by
# the Free Software Foundation, version 3 of the License.
#
# This program is distributed in the hope that it will be useful,
# but WITHOUT ANY WARRANTY; without even the implied warranty of
# MERCHANTABILITY or FITNESS FOR A PARTICULAR PURPOSE.  See the
# GNU General Public License for more details.
#
# You should have received a copy of the GNU General Public License
# along with this program.  If not, see <http://www.gnu.org/licenses/>.
#*/

`timescale 1 ns / 100 ps

module system_tb;

//----------------------------------------------------------------------------
// Parameter (may differ for physical synthesis)
//----------------------------------------------------------------------------
parameter tck              = 20;       // clock period in ns
parameter uart_baud_rate   = 1152000;  // uart baud rate for simulation 

parameter clk_freq = 1000000000 / tck; // Frequenzy in HZ
//----------------------------------------------------------------------------
//
//----------------------------------------------------------------------------
reg        clk_tb;
reg        rst_tb;
reg			cont_tb;
reg			equal_tb;
reg			[7:0]dividiendo_tb,i_a_tb,i_b_tb;
reg			[7:0]n_valor_tb;
wire       led_tb;
//----------------------------------------------------------------------------
// UART STUFF (testbench uart, simulating a comm. partner)
//----------------------------------------------------------------------------
wire         uart_rxd_tb;
wire         uart_txd_tb;

//----------------------------------------------------------------------------
// Device Under Test 
//----------------------------------------------------------------------------
comparador #(
	.N ( 8 )
	) comp(
	.i_a ( i_a_tb),
	.i_b (i_b_tb)
	);


shift #(
	.N	(	8	)
	) dut  (
	//.clk(	clk_tb	),
	// Debug
	.rst(	rst_tb	),
	.cont( cont_tb),
	.equal( equal_tb ),
	.n_valor( n_valor_tb ),
	.dividiendo( dividiendo_tb)

	// Uart
	);


	/* Clocking device */
// Remember this is only for simulation. It never will be syntetizable //
initial         clk_tb <= 0;
always #(tck/2) clk_tb <= ~clk_tb;

/* Simulation setup */
initial begin
	//set the file for loggin simulation data
	$dumpfile("system_tb.vcd"); 
	//$monitor("%b,%b,%b",clk_tb,rst_tb,led_tb);
	//export all signals in the simulation viewer
	$dumpvars(-1, dut);
	$dumpvars(-1, comp);
	//$dumpvars(-1,clk_tb,rst_tb);
	#0 i_a_tb <= 8'b00000100;
	#0 i_b_tb <= 8'b00001010;
	
	#0 dividiendo_tb <= 8'b11001011;
	#0 n_valor_tb <= 8'd5;
	#0 equal_tb <= 0;
	#0  rst_tb <= 1;
	#0 cont_tb <= 0;
	#80 rst_tb <= 0;
	#100 cont_tb <= 1;

	#0 i_a_tb <= 8'b00000100;
	#0 i_b_tb <= 8'b00000010;

	#20 cont_tb <= 0;
	#100 cont_tb <= 1;
	#20 cont_tb <= 0;
	#100 cont_tb <= 1;
	#20 cont_tb <= 0;
	#100 cont_tb <= 1;
	#20 cont_tb <= 0;
	#50 equal_tb <= 1;
	#50 equal_tb <= 0;
	#(tck*100000) $finish;
	end
	endmodule

divisor/simulation/system_tb.vcd
$date
	Fri Aug 14 11:52:04 2015
$end
$version
	Icarus Verilog
$end
$timescale
	100ps
$end
$scope module system_tb $end
$scope module dut $end
$var wire 1 ! cont $end
$var wire 8 " dividiendo [7:0] $end
$var wire 1 # equal $end
$var wire 8 $ n_valor [7:0] $end
$var wire 8 % q [7:0] $end
$var wire 1 & rst $end
$var wire 8 ' w_salida [7:0] $end
$var wire 8 ( w_select_bit [7:0] $end
$var reg 8 ) r_dividiendo [7:0] $end
$var reg 8 * salida [7:0] $end
$var reg 8 + select_bit [7:0] $end
$upscope $end
$upscope $end
$scope module system_tb $end
$scope module comp $end
$var wire 8 , i_a [7:0] $end
$var wire 8 - i_b [7:0] $end
$var wire 8 . o_resta [7:0] $end
$var wire 1 / o_signal $end
$upscope $end
$upscope $end
$enddefinitions $end
#0
$dumpvars
0/
b11111010 .
b1010 -
b100 ,
b111 +
b0 *
b11001011 )
b1 (
b1 '
1&
b0 %
b101 $
0#
b11001011 "
0!
$end
#800
0&
#1800
b11 '
1/
b110 +
b1 *
b1 %
b10 -
b10 .
1!
#2000
0!
#3000
b101 +
b110 '
b0 (
b11 *
b11 %
1!
#3200
0!
#4200
b1100 '
b100 +
b110 *
b110 %
1!
#4400
0!
#5400
b11 +
b11001 '
b1 (
b1100 *
b1100 %
1!
#5600
0!
#6100
b1011 '
b101 *
b101 %
1#
#6600
0#
